{
    "content_creator": [
      {
        "id": "15da7bc5-f23c-46b5-9ebd-abf7438337c3",
        "Facebook": {
          "id": "58d86a22-bde3-478b-b708-4e6bf193702c",
          "thumbnail": "https://www.google.com/url?sa=i&url=https%3A%2F%2Fwww.freepik.com%2Ffree-photos-vectors%2Favatar&psig=AOvVaw0dHIngPYqafTA4_rGs7RR3&ust=1715185630686000&source=images&cd=vfe&opi=89978449&ved=0CBIQjRxqFwoTCOiDnsb6-4UDFQAAAAAdAAAAABAE",
          "name": "Akeem",
          "username": "@Akeem.Weber",
          "intro": "Self-taught programmer with free online resources.",
          "email": "akeem@gmail.com",
          "permalink_url": "https://worn-television.org",
          "category": "Education",
          "followers": 1107,
          "content_count": 73,
          "page_views_day": 643,
          "page_post_engagements": 127
        },
        "Instagram": {
          "id": "70f033bb-f69d-4220-9a65-4049a0d9cd1c",
          "profile_picture": "https://picsum.photos/seed/7L6T28WMHM/640/480",
          "name": "akeem",
          "followers_count": 1107,
          "media_count": 1,
          "reach": 738,
          "profile_views": 158,
          "male_follower_demographics": 805,
          "female_follower_demographics": 6770,
          "unknown_follower_demographic": 3517
        },
        "Tiktok": {
          "id": "33deb878-a733-4bdd-86a8-e8ab0ef70b9f",
          "display_name": "Akeem",
          "handle_name": "@akeem",
          "followers_count": 1718,
          "videos_count": 45,
          "average_views": 997,
          "average_likes": 181,
          "average_shares": 987,
          "average_comments": 932,
          "engagement_rate": 4.48
        }
      },
      {
        "id": "ca3bb2ef-6de0-4cc1-92a1-da8baac9b834",
        "Facebook": {
          "id": "1b2aa31b-e544-434c-836d-c4cde93bba52",
          "thumbnail": "https://picsum.photos/seed/vOvLYdo/640/480",
          "name": "Beryl Carissa",
          "username": "@beryl_carissa",
          "intro": "Giving you the best content that can make you laugh everyday.",
          "email": "beryl_carissa@yahoo.com",
          "permalink_url": "https://brilliant-fallacy.info/",
          "category": "Entertainment",
          "followers": 8539,
          "content_count": 50,
          "page_views_day": 168,
          "page_post_engagements": 638
        },
        "Instagram": {
          "id": "2dbf15d9-80ad-4ab9-b3f1-1452519cb403",
          "profile_picture": "https://picsum.photos/seed/6Os0jlbIG/640/480",
          "name": "Beryl Carissa",
          "followers_count": 5600,
          "media_count": 50,
          "reach": 395,
          "profile_views": 664,
          "male_follower_demographics": 6450,
          "female_follower_demographics": 2403,
          "unknown_follower_demographic": 8200
        },
        "Tiktok": {
          "id": "a7a4a593-f43e-442c-8c97-93e623fa00e5",
          "display_name": "Beryl Carissa",
          "handle_name": "@beryl_carissa",
          "followers_count": 8975,
          "videos_count": 34,
          "average_views": 398,
          "average_likes": 982,
          "average_shares": 919,
          "average_comments": 196,
          "engagement_rate": 1.85
        }
      },
      {
        "id": "c8e6e8ce-e01f-4246-ae56-5c590476a23f",
        "Facebook": {
          "id": "9ccb1345-dfd5-440e-bcb8-28c110af2ef7",
          "thumbnail": "https://picsum.photos/seed/tCFe7GrnRV/640/480",
          "name": "Mike Murphy",
          "username": "@mike.murphy",
          "intro": "Financial freedom is no longer a dream for anyone!",
          "email": "mike.murphy@gmail.com",
          "permalink_url": "https://best-fax.com",
          "category": "Financial",
          "followers": 2827,
          "content_count": 50,
          "page_views_day": 619,
          "page_post_engagements": 200
        },
        "Instagram": {
          "id": "de40a8c1-05f8-43a9-97d5-9317883fc415",
          "profile_picture": "https://picsum.photos/seed/5awtL6/640/480",
          "name": "Mike Murphy",
          "followers_count": 3065,
          "media_count": 69,
          "reach": 787,
          "profile_views": 441,
          "male_follower_demographics": 1125,
          "female_follower_demographics": 6731,
          "unknown_follower_demographic": 1376
        },
        "Tiktok": {
          "id": "c8329578-da68-4d44-adc9-2845217dcae1",
          "display_name": "Mike Murphy",
          "handle_name": "@mike_murphy",
          "followers_count": 3184,
          "videos_count": 38,
          "average_views": 555,
          "average_likes": 773,
          "average_shares": 295,
          "average_comments": 129,
          "engagement_rate": 3.19
        }
      }
    ]
  }